mutf8/__init__.py
mutf8/cmutf8.cpython-36m-darwin.so
mutf8/mutf8.py
mutf8-1.0.6.dist-info/LICENCE
mutf8-1.0.6.dist-info/METADATA
mutf8-1.0.6.dist-info/WHEEL
mutf8-1.0.6.dist-info/top_level.txt
mutf8-1.0.6.dist-info/RECORD
