Metadata-Version: 2.1
Name: mutf8
Version: 1.0.6
Summary: Fast MUTF-8 encoder & decoder
Home-page: http://github.com/TkTech/mutf8
Author: Tyler Kennedy
Author-email: tk@tkte.ch
License: UNKNOWN
Keywords: mutf-8,cesu-8,jvm
Platform: UNKNOWN
Classifier: Programming Language :: Python :: 3
Classifier: License :: OSI Approved :: MIT License
Classifier: Operating System :: OS Independent
Classifier: Intended Audience :: Developers
License-File: LICENCE
Provides-Extra: test
Requires-Dist: pytest ; extra == 'test'
Requires-Dist: pytest-benchmark ; extra == 'test'
